[
	{
		"name": "$construct",
		"order": 1,
		"clientexec": false,
		"pvardefs": [

		],
		"lvardefs": [

		]
	},
	{
		"name": "$destruct",
		"order": 2,
		"clientexec": false,
		"pvardefs": [

		],
		"lvardefs": [

		]
	},
	{
		"name": "buildItems",
		"order": 3,
		"clientexec": false,
		"pvardefs": [

		],
		"lvardefs": [
			{
				"name": "debugPanel",
				"order": 1,
				"type": "kObjectref",
				"subtype": "omnis-dashboard.oDebugPanel",
				"sublen": 0
			},
			{
				"name": "loadingPanel",
				"order": 2,
				"type": "kObjectref",
				"subtype": "omnis-dashboard.oLoadingPanel",
				"sublen": 0
			}
		]
	},
	{
		"name": "buildThemes",
		"order": 4,
		"clientexec": false,
		"pvardefs": [

		],
		"lvardefs": [
			{
				"name": "theme",
				"order": 1,
				"type": "kCharacter",
				"subtype": "kSimplechar",
				"sublen": 100000000
			}
		]
	},
	{
		"name": "save",
		"order": 5,
		"clientexec": false,
		"pvardefs": [

		],
		"lvardefs": [

		]
	},
	{
		"name": "updatePanels",
		"order": 6,
		"clientexec": false,
		"pvardefs": [
			{
				"name": "pPayload",
				"order": 1,
				"type": "kCharacter",
				"subtype": "kSimplechar",
				"sublen": 100000000,
				"param": 1
			}
		],
		"lvardefs": [

		]
	}
]
